meinefunct/__init__.py
meinefunct/meinefunction.py
meinefunct-0.1.0.dist-info/METADATA
meinefunct-0.1.0.dist-info/WHEEL
meinefunct-0.1.0.dist-info/top_level.txt
meinefunct-0.1.0.dist-info/RECORD
