Metadata-Version: 2.1
Name: meinefunct
Version: 0.1.0
Summary: My first Python library
Author: homecamper
License: MIT
